aiotraxx/__init__.py
aiotraxx/__version__.py
aiotraxx/auth.py
aiotraxx/controllers.py
aiotraxx/exceptions.py
aiotraxx/http.py
aiotraxx/models.py
aiotraxx/py.typed
aiotraxx/stream.py
aiotraxx/subscriber.py
aiotraxx-0.0.1.dist-info/LICENSE
aiotraxx-0.0.1.dist-info/METADATA
aiotraxx-0.0.1.dist-info/WHEEL
aiotraxx-0.0.1.dist-info/top_level.txt
aiotraxx-0.0.1.dist-info/RECORD
